README.rst
boltzmannclean.py
setup.py
boltzmannclean.egg-info/PKG-INFO
boltzmannclean.egg-info/SOURCES.txt
boltzmannclean.egg-info/dependency_links.txt
boltzmannclean.egg-info/requires.txt
boltzmannclean.egg-info/top_level.txt