Metadata-Version: 1.0
Name: boltzmannclean
Version: 0.1.2
Summary: Fill missing values in DataFrames with Restricted Boltzmann Machines
Home-page: https://github.com/facultyai/boltzmannclean
Author: Faculty
Author-email: opensource@faculty.ai
License: Apache 2.0
Platform: UNKNOWN
